whatlang_pyo3-0.6.0.dist-info/METADATA
whatlang_pyo3-0.6.0.dist-info/WHEEL
whatlang_pyo3-0.6.0.dist-info/entry_points.txt
whatlang_pyo3-0.6.0.dist-info/license_files/LICENSE
whatlang/__init__.py
whatlang/__init__.pyi
whatlang/py.typed
whatlang/whatlang.cpython-311-darwin.so
whatlang_pyo3-0.6.0.dist-info/RECORD
