Metadata-Version: 2.1
Name: whatlang-pyo3
Version: 0.6.0
Classifier: Programming Language :: Rust
Classifier: Programming Language :: Python :: Implementation :: CPython
Classifier: Programming Language :: Python :: Implementation :: PyPy
License-File: LICENSE
Summary: Python bindings for whatlang using pyo3
Keywords: whatlang,pyo3,python,bindings,natural language,language detection
Author: Omar MHAIMDAT
Author-email: Omar MHAIMDAT <omarmhaidmat@gmail.com>
License: MIT
Requires-Python: >=3.7
Project-URL: Source Code, https://github.com/omarmhaimdat/whatlang-pyo3
